{
  "id": "3756431",
  "name": "myworld",
  "font_family": "iconfont",
  "css_prefix_text": "icon-",
  "description": "",
  "glyphs": [
    {
      "icon_id": "1467351",
      "name": "github",
      "font_class": "github",
      "unicode": "e691",
      "unicode_decimal": 59025
    },
    {
      "icon_id": "77156",
      "name": "微信",
      "font_class": "weixin1",
      "unicode": "e600",
      "unicode_decimal": 58880
    },
    {
      "icon_id": "4936984",
      "name": "QQ",
      "font_class": "QQ",
      "unicode": "e882",
      "unicode_decimal": 59522
    }
  ]
}
